{
  "resourceType" : "ValueSet",
  "id" : "VSRazonEstadoDispensacion",
  "text" : {
    "status" : "generated",
    "div" : "<div xmlns=\"http://www.w3.org/1999/xhtml\"><ul><li>Include all codes defined in <a href=\"CodeSystem-CSRazonEstadoDispensacion.html\"><code>https://rme.hl7chile.cl/CodeSystem/CSRazonEstadoDispensacion</code></a></li></ul></div>"
  },
  "url" : "https://rme.hl7chile.cl/ValueSet/VSRazonEstadoDispensacion",
  "version" : "0.9",
  "name" : "VSRazonEstadoDispensacion",
  "title" : "Razón del cambio de estado (Dispensación)",
  "status" : "active",
  "date" : "2022-01-18T00:00:00-03:00",
  "contact" : [{
    "name" : "HL7 Chile",
    "telecom" : [{
      "system" : "email",
      "value" : "chair@hl7chile.cl"
    }]
  }],
  "description" : "Códigos que indican la razón por la cual una Dispensación ha cambiado su estado",
  "jurisdiction" : [{
    "coding" : [{
      "system" : "urn:iso:std:iso:3166",
      "code" : "CL",
      "display" : "Chile"
    }]
  }],
  "compose" : {
    "include" : [{
      "system" : "https://rme.hl7chile.cl/CodeSystem/CSRazonEstadoDispensacion"
    }]
  }
}